huaweicloudsdkfrs/__init__.py
huaweicloudsdkfrs/v2/__init__.py
huaweicloudsdkfrs/v2/frs_async_client.py
huaweicloudsdkfrs/v2/frs_client.py
huaweicloudsdkfrs/v2/model/__init__.py
huaweicloudsdkfrs/v2/model/actions_list.py
huaweicloudsdkfrs/v2/model/add_faces_base64_req.py
huaweicloudsdkfrs/v2/model/add_faces_by_base64_request.py
huaweicloudsdkfrs/v2/model/add_faces_by_base64_response.py
huaweicloudsdkfrs/v2/model/add_faces_by_file_request.py
huaweicloudsdkfrs/v2/model/add_faces_by_file_request_body.py
huaweicloudsdkfrs/v2/model/add_faces_by_file_response.py
huaweicloudsdkfrs/v2/model/add_faces_by_url_request.py
huaweicloudsdkfrs/v2/model/add_faces_by_url_response.py
huaweicloudsdkfrs/v2/model/add_faces_url_req.py
huaweicloudsdkfrs/v2/model/attributes.py
huaweicloudsdkfrs/v2/model/attributes_expression.py
huaweicloudsdkfrs/v2/model/batch_delete_faces_request.py
huaweicloudsdkfrs/v2/model/batch_delete_faces_response.py
huaweicloudsdkfrs/v2/model/bounding_box.py
huaweicloudsdkfrs/v2/model/compare_face.py
huaweicloudsdkfrs/v2/model/compare_face_by_base64_request.py
huaweicloudsdkfrs/v2/model/compare_face_by_base64_response.py
huaweicloudsdkfrs/v2/model/compare_face_by_file_request.py
huaweicloudsdkfrs/v2/model/compare_face_by_file_request_body.py
huaweicloudsdkfrs/v2/model/compare_face_by_file_response.py
huaweicloudsdkfrs/v2/model/compare_face_by_url_request.py
huaweicloudsdkfrs/v2/model/compare_face_by_url_response.py
huaweicloudsdkfrs/v2/model/create_face_set_req.py
huaweicloudsdkfrs/v2/model/create_face_set_request.py
huaweicloudsdkfrs/v2/model/create_face_set_response.py
huaweicloudsdkfrs/v2/model/delete_face_by_external_image_id_request.py
huaweicloudsdkfrs/v2/model/delete_face_by_external_image_id_response.py
huaweicloudsdkfrs/v2/model/delete_face_by_face_id_request.py
huaweicloudsdkfrs/v2/model/delete_face_by_face_id_response.py
huaweicloudsdkfrs/v2/model/delete_face_set_request.py
huaweicloudsdkfrs/v2/model/delete_face_set_response.py
huaweicloudsdkfrs-3.1.184.dist-info/METADATA
huaweicloudsdkfrs-3.1.184.dist-info/WHEEL
huaweicloudsdkfrs-3.1.184.dist-info/licenses/LICENSE
huaweicloudsdkfrs-3.1.184.dist-info/RECORD
